pyNetX/__init__.py
pyNetX/pyNetX.cpython-311-x86_64-linux-gnu.so
pynetx-1.0.9.data/data/CMakeLists.txt
pynetx-1.0.9.data/data/LICENSE
pynetx-1.0.9.data/data/README.md
pynetx-1.0.9.data/data/setup.py
pynetx-1.0.9.data/data/include/netconf_client.hpp
pynetx-1.0.9.data/data/include/notification_reactor.hpp
pynetx-1.0.9.data/data/include/notification_reactor_manager.hpp
pynetx-1.0.9.data/data/include/thread_pool.hpp
pynetx-1.0.9.data/data/include/thread_pool_global.hpp
pynetx-1.0.9.data/data/src/bindings.cpp
pynetx-1.0.9.data/data/src/netconf_client_async.cpp
pynetx-1.0.9.data/data/src/netconf_client_blocking.cpp
pynetx-1.0.9.data/data/src/netconf_client_common.cpp
pynetx-1.0.9.data/data/src/netconf_client_helpers.cpp
pynetx-1.0.9.data/data/src/netconf_client_non_blocking.cpp
pynetx-1.0.9.data/data/src/netconf_client_sync.cpp
pynetx-1.0.9.data/data/src/notification_reactor.cpp
pynetx-1.0.9.data/data/src/notification_reactor_manager.cpp
pynetx-1.0.9.data/data/src/thread_pool_global.cpp
pynetx.libs/libtinyxml2-92ecb01a.so.2.1.0
pynetx-1.0.9.dist-info/METADATA
pynetx-1.0.9.dist-info/WHEEL
pynetx-1.0.9.dist-info/top_level.txt
pynetx-1.0.9.dist-info/RECORD
pynetx-1.0.9.dist-info/licenses/LICENSE
