Metadata-Version: 2.4
Name: pyNetX
Version: 1.0.9
Summary: NETCONF client with truly async capabilities
Author: Sambhu Nampoothiri G
Author-email: Sambhu Nampoothiri G <get4sambhugn@gmail.com>
License: Apache-2.0
Requires-Python: >=3.11
License-File: LICENSE
Dynamic: author
Dynamic: license-file
